setup.py
cartodb/__init__.py
cartodb/cartodb.py
cartodb.egg-info/PKG-INFO
cartodb.egg-info/SOURCES.txt
cartodb.egg-info/dependency_links.txt
cartodb.egg-info/requires.txt
cartodb.egg-info/top_level.txt