Metadata-Version: 1.1
Name: cartodb
Version: 0.7
Summary: client to access cartodb api
Home-page: https://github.com/Vizzuality/cartodb
Author: Javi Santana
Author-email: jsantana@vizzuality.com
License: UNKNOWN
Platform: UNKNOWN
Requires: oauth2
